{
  "project_info": {
    "project_number": "724321742837",
    "project_id": "foodsnapauth-a249f",
    "storage_bucket": "foodsnapauth-a249f.appspot.com"
  },
  "client": [
    {
      "client_info": {
        "mobilesdk_app_id": "1:724321742837:android:8f8b98e443e4aee85ababc",
        "android_client_info": {
          "package_name": "com.example.foodsnap"
        }
      },
      "oauth_client": [
        {
          "client_id": "724321742837-u3vhvl8t3op9097cr8p4ks929rj1enr7.apps.googleusercontent.com",
          "client_type": 3
        }
      ],
      "api_key": [
        {
          "current_key": "AIzaSyB0iBVmuXJBE7ABVqoed02-cK3GpEpONjE"
        }
      ],
      "services": {
        "appinvite_service": {
          "other_platform_oauth_client": [
            {
              "client_id": "724321742837-ok6obo4s2jbjt273f998u4qrb892pl3s.apps.googleusercontent.com",
              "client_type": 3
            }
          ]
        }
      }
    }
  ],
  "configuration_version": "1"
}